MANIFEST.in
README.md
setup.cfg
setup.py
ltspice2svg/__init__.py
ltspice2svg.egg-info/PKG-INFO
ltspice2svg.egg-info/SOURCES.txt
ltspice2svg.egg-info/dependency_links.txt
ltspice2svg.egg-info/requires.txt
ltspice2svg.egg-info/top_level.txt
ltspice2svg/Resource/sym/FerriteBead.txt
ltspice2svg/Resource/sym/FerriteBead2.txt
ltspice2svg/Resource/sym/ISO16750-2.txt
ltspice2svg/Resource/sym/ISO7637-2.txt
ltspice2svg/Resource/sym/LED.txt
ltspice2svg/Resource/sym/LM7805.txt
ltspice2svg/Resource/sym/LM7812.txt
ltspice2svg/Resource/sym/LM7815.txt
ltspice2svg/Resource/sym/SOAtherm-HeatSink.txt
ltspice2svg/Resource/sym/SOAtherm-PCB.txt
ltspice2svg/Resource/sym/TVSdiode.txt
ltspice2svg/Resource/sym/bi.txt
ltspice2svg/Resource/sym/bi2.txt
ltspice2svg/Resource/sym/bv.txt
ltspice2svg/Resource/sym/cap.txt
ltspice2svg/Resource/sym/csw.txt
ltspice2svg/Resource/sym/current.txt
ltspice2svg/Resource/sym/diode.txt
ltspice2svg/Resource/sym/e.txt
ltspice2svg/Resource/sym/e2.txt
ltspice2svg/Resource/sym/f.txt
ltspice2svg/Resource/sym/g.txt
ltspice2svg/Resource/sym/g2.txt
ltspice2svg/Resource/sym/h.txt
ltspice2svg/Resource/sym/ind.txt
ltspice2svg/Resource/sym/ind2.txt
ltspice2svg/Resource/sym/load.txt
ltspice2svg/Resource/sym/load2.txt
ltspice2svg/Resource/sym/lpnp.txt
ltspice2svg/Resource/sym/ltline.txt
ltspice2svg/Resource/sym/mesfet.txt
ltspice2svg/Resource/sym/njf.txt
ltspice2svg/Resource/sym/nmos.txt
ltspice2svg/Resource/sym/nmos4.txt
ltspice2svg/Resource/sym/npn.txt
ltspice2svg/Resource/sym/npn2.txt
ltspice2svg/Resource/sym/npn3.txt
ltspice2svg/Resource/sym/npn4.txt
ltspice2svg/Resource/sym/pjf.txt
ltspice2svg/Resource/sym/pmos.txt
ltspice2svg/Resource/sym/pmos4.txt
ltspice2svg/Resource/sym/pnp.txt
ltspice2svg/Resource/sym/pnp2.txt
ltspice2svg/Resource/sym/pnp4.txt
ltspice2svg/Resource/sym/polcap.txt
ltspice2svg/Resource/sym/res.txt
ltspice2svg/Resource/sym/res2.txt
ltspice2svg/Resource/sym/schottky.txt
ltspice2svg/Resource/sym/sw.txt
ltspice2svg/Resource/sym/tline.txt
ltspice2svg/Resource/sym/varactor.txt
ltspice2svg/Resource/sym/voltage.txt
ltspice2svg/Resource/sym/zener.txt
ltspice2svg/Resource/sym/ADC/AD4002.txt
ltspice2svg/Resource/sym/ADC/AD4003.txt
